invoice_merger/__init__.py
invoice_merger/__main__.py
invoice_merger/cli.py
invoice_merger/merger.py
invoice_merger-1.2.0.dist-info/licenses/LICENSE
invoice_merger-1.2.0.dist-info/METADATA
invoice_merger-1.2.0.dist-info/WHEEL
invoice_merger-1.2.0.dist-info/entry_points.txt
invoice_merger-1.2.0.dist-info/top_level.txt
invoice_merger-1.2.0.dist-info/RECORD
