Metadata-Version: 2.4
Name: invoice-merger
Version: 1.2.0
Summary: 将电子发票按月份自动分组并合并到A4纸上，便于打印报销
Author-email: Your Name <your.email@example.com>
License-Expression: MIT
Project-URL: Homepage, https://github.com/luzhongqiu/invoice-merger
Project-URL: Bug Reports, https://github.com/luzhongqiu/invoice-merger/issues
Project-URL: Source, https://github.com/luzhongqiu/invoice-merger
Keywords: invoice,pdf,merge,train-ticket,电子发票
Classifier: Development Status :: 4 - Beta
Classifier: Intended Audience :: End Users/Desktop
Classifier: Programming Language :: Python :: 3
Classifier: Programming Language :: Python :: 3.8
Classifier: Programming Language :: Python :: 3.9
Classifier: Programming Language :: Python :: 3.10
Classifier: Programming Language :: Python :: 3.11
Classifier: Programming Language :: Python :: 3.12
Classifier: Topic :: Office/Business
Classifier: Topic :: Utilities
Requires-Python: >=3.8
License-File: LICENSE
Requires-Dist: pymupdf>=1.20.0
Requires-Dist: tqdm>=4.60.0
Provides-Extra: dev
Requires-Dist: pytest>=7.0.0; extra == "dev"
Requires-Dist: black>=22.0.0; extra == "dev"
Requires-Dist: flake8>=4.0.0; extra == "dev"
Dynamic: license-file
